rddlrepository/__init__.py
rddlrepository/main.py
rddlrepository/archive/__init__.py
rddlrepository/archive/arcade/__init__.py
rddlrepository/archive/arcade/Blackjack/__init__.py
rddlrepository/archive/arcade/Blackjack/domain.rddl
rddlrepository/archive/arcade/Blackjack/instance0.rddl
rddlrepository/archive/arcade/Eight/__init__.py
rddlrepository/archive/arcade/Eight/domain.rddl
rddlrepository/archive/arcade/Eight/instance0.rddl
rddlrepository/archive/arcade/Eight/instance1.rddl
rddlrepository/archive/arcade/Pong/PongViz.py
rddlrepository/archive/arcade/Pong/__init__.py
rddlrepository/archive/arcade/Pong/domain.rddl
rddlrepository/archive/arcade/Pong/instance0.rddl
rddlrepository/archive/arcade/Sokoban/__init__.py
rddlrepository/archive/arcade/Sokoban/domain.rddl
rddlrepository/archive/arcade/Sokoban/instance0.rddl
rddlrepository/archive/arcade/Sudoku/__init__.py
rddlrepository/archive/arcade/Sudoku/domain.rddl
rddlrepository/archive/arcade/Sudoku/instance0.rddl
rddlrepository/archive/arcade/Sudoku/instance1.rddl
rddlrepository/archive/arcade/Tetris/__init__.py
rddlrepository/archive/arcade/Tetris/domain.rddl
rddlrepository/archive/arcade/Tetris/instance0.rddl
rddlrepository/archive/arcade/TowerOfHanoi/__init__.py
rddlrepository/archive/arcade/TowerOfHanoi/domain.rddl
rddlrepository/archive/arcade/TowerOfHanoi/instance0.rddl
rddlrepository/archive/arcade/Zombies/__init__.py
rddlrepository/archive/arcade/Zombies/domain.rddl
rddlrepository/archive/arcade/Zombies/instance0.rddl
rddlrepository/archive/arcade/Zombies/instance1.rddl
rddlrepository/archive/arcade/Zombies/instance2.rddl
rddlrepository/archive/arcade/Zombies/instance3.rddl
rddlrepository/archive/competitions/__init__.py
rddlrepository/archive/competitions/IPPC2011/__init__.py
rddlrepository/archive/competitions/IPPC2011/CooperativeRecon/__init__.py
rddlrepository/archive/competitions/IPPC2011/CooperativeRecon/MDP/__init__.py
rddlrepository/archive/competitions/IPPC2011/CooperativeRecon/MDP/domain.rddl
rddlrepository-2.1.dist-info/licenses/LICENSE.MD
rddlrepository-2.1.dist-info/METADATA
rddlrepository-2.1.dist-info/WHEEL
rddlrepository-2.1.dist-info/top_level.txt
rddlrepository-2.1.dist-info/RECORD
