Metadata-Version: 2.4
Name: rddlrepository
Version: 2.1
Summary: Home for all things RDDL
Home-page: https://github.com/pyrddlgym-project/rddlrepository
Author: Ayal Taitler, Michael Gimelfarb, Scott Sanner
Author-email: ataitler@gmail.com, mike.gimelfarb@mail.utoronto.ca, ssanner@mie.utoronto.ca
License: MIT License
Classifier: Development Status :: 5 - Production/Stable
Classifier: Intended Audience :: Science/Research
Classifier: License :: OSI Approved :: MIT License
Classifier: Natural Language :: English
Classifier: Operating System :: OS Independent
Classifier: Programming Language :: Python :: 3
Classifier: Topic :: Scientific/Engineering :: Artificial Intelligence
Requires-Python: >=3.8
License-File: LICENSE.MD
Requires-Dist: numpy
Dynamic: author
Dynamic: author-email
Dynamic: classifier
Dynamic: home-page
Dynamic: license
Dynamic: license-file
Dynamic: requires-dist
Dynamic: requires-python
Dynamic: summary
